{"model":{"version":3,"nodes":[{"name":"RootNode","position":[0,0,0],"rotation":[0,0,0],"scale":[0.01,0.01,0.01],"scaleCompensation":false},{"name":"Main_Dummy","position":[0,0,0],"rotation":[-90,0,0],"scale":[0.316508,0.316508,0.316508],"scaleCompensation":false},{"name":"Dummy_02","position":[0,1.00342e-05,-229.557],"rotation":[0,0,0],"scale":[0.25373,0.25373,0.25373],"scaleCompensation":false},{"name":"Dummy_03","position":[0,2.26769e-05,-518.787],"rotation":[0,0,0],"scale":[1,1,1],"scaleCompensation":false},{"name":"Dummy_04","position":[0,2.4301e-05,-555.943],"rotation":[0,0,0],"scale":[1,1,1],"scaleCompensation":false},{"name":"Dummy_05","position":[0,2.56047e-05,-10172.9],"rotation":[20,65,0],"scale":[1.35661e-08,1.35661e-08,1.35661e-08],"scaleCompensation":false},{"name":"sub_02","position":[1018.22,11.21,-10572.7],"rotation":[-0,90,0],"scale":[5.16666e-09,5.16666e-09,5.16666e-09],"scaleCompensation":false},{"name":"sub_03","position":[-11.2096,998.166,-10572.7],"rotation":[-90,-0,0],"scale":[5.16666e-09,5.16666e-09,5.16666e-09],"scaleCompensation":false},{"name":"sub_04","position":[-1012.78,-11.2092,-10572.7],"rotation":[-0,-90,0],"scale":[5.16666e-09,5.16666e-09,5.16666e-09],"scaleCompensation":false},{"name":"sub_01","position":[11.2096,-1016.61,-10572.7],"rotation":[90,-0,0],"scale":[5.16666e-09,5.16666e-09,5.16666e-09],"scaleCompensation":false}],"parents":[-1,0,1,2,3,4,4,4,4,4],"skins":[],"morphs":[],"vertices":[],"meshes":[],"meshInstances":[]}}